MANIFEST.in
README.rst
eventlog.py
requirements.txt
setup.py
tcloghandler.py
eventlog_writer.egg-info/PKG-INFO
eventlog_writer.egg-info/SOURCES.txt
eventlog_writer.egg-info/dependency_links.txt
eventlog_writer.egg-info/requires.txt
eventlog_writer.egg-info/top_level.txt